pcloud_sdk/__init__.py
pcloud_sdk/app.py
pcloud_sdk/cli.py
pcloud_sdk/config.py
pcloud_sdk/core.py
pcloud_sdk/exceptions.py
pcloud_sdk/file_operations.py
pcloud_sdk/folder_operations.py
pcloud_sdk/progress_utils.py
pcloud_sdk/request.py
pcloud_sdk/response.py
pcloud_sdk/user_operations.py
pcloud_sdk_python-1.0.0.dist-info/licenses/LICENSE
pcloud_sdk_python-1.0.0.dist-info/METADATA
pcloud_sdk_python-1.0.0.dist-info/WHEEL
pcloud_sdk_python-1.0.0.dist-info/entry_points.txt
pcloud_sdk_python-1.0.0.dist-info/top_level.txt
pcloud_sdk_python-1.0.0.dist-info/RECORD
