Metadata-Version: 2.4
Name: pcloud-sdk-python
Version: 1.0.0
Summary: Modern Python SDK for pCloud API with automatic token management and progress tracking
Home-page: https://github.com/yourusername/pcloud-sdk-python
Author: pCloud SDK Python Contributors (Koffi joel)
Author-email: "pCloud SDK Contributors (Koffi joel)" <jolli644@gmail.com>
License: MIT
Project-URL: Homepage, https://github.com/koffiisen/pcloud-sdk-python
Project-URL: Documentation, https://pcloud-sdk-python.readthedocs.io/
Project-URL: Repository, https://github.com/koffiisen/pcloud-sdk-python.git
Project-URL: Bug Tracker, https://github.com/koffiisen/pcloud-sdk-python/issues
Project-URL: Changelog, https://github.com/koffiisen/pcloud-sdk-python/blob/main/CHANGELOG.md
Keywords: pcloud,cloud,storage,api,sdk,file,upload,download
Classifier: Development Status :: 5 - Production/Stable
Classifier: Intended Audience :: Developers
Classifier: License :: OSI Approved :: MIT License
Classifier: Operating System :: OS Independent
Classifier: Programming Language :: Python :: 3
Classifier: Programming Language :: Python :: 3.7
Classifier: Programming Language :: Python :: 3.8
Classifier: Programming Language :: Python :: 3.9
Classifier: Programming Language :: Python :: 3.10
Classifier: Programming Language :: Python :: 3.11
Classifier: Programming Language :: Python :: 3.12
Classifier: Topic :: Internet :: WWW/HTTP
Classifier: Topic :: Software Development :: Libraries :: Python Modules
Classifier: Topic :: System :: Filesystems
Requires-Python: >=3.7
License-File: LICENSE
Requires-Dist: requests>=2.25.0
Provides-Extra: dev
Requires-Dist: pytest>=6.0; extra == "dev"
Requires-Dist: pytest-cov>=2.10; extra == "dev"
Requires-Dist: black>=21.0; extra == "dev"
Requires-Dist: isort>=5.0; extra == "dev"
Requires-Dist: pre-commit>=2.15; extra == "dev"
Requires-Dist: mkdocs>=1.5.0; extra == "dev"
Requires-Dist: mkdocs-material>=9.0.0; extra == "dev"
Requires-Dist: mkdocstrings[python]>=0.20.0; extra == "dev"
Provides-Extra: test
Requires-Dist: pytest>=6.0; extra == "test"
Requires-Dist: pytest-cov>=2.10; extra == "test"
Requires-Dist: responses>=0.18.0; extra == "test"
Dynamic: author
Dynamic: home-page
Dynamic: license-file
Dynamic: requires-python
